setup.py
ppmessage_mqtt/__init__.py
ppmessage_mqtt/ppauth.py
ppmessage_mqtt/ppmt.py
ppmessage_mqtt/ppmtdb.py
ppmessage_mqtt/yourauth.py
ppmessage_mqtt.egg-info/PKG-INFO
ppmessage_mqtt.egg-info/SOURCES.txt
ppmessage_mqtt.egg-info/dependency_links.txt
ppmessage_mqtt.egg-info/requires.txt
ppmessage_mqtt.egg-info/top_level.txt