Metadata-Version: 1.1
Name: ppmessage-mqtt
Version: 1.0.6
Summary: A Python mqtt server, originally developed at PPMessage.
Home-page: http://www.ppmessage.com
Author: ppmessage.com
Author-email: dingguijin@gmail.com
License: http://www.apache.org/licenses/LICENSE-2.0
Keywords: mqtt server ppmessage
Platform: UNKNOWN
Classifier: License :: OSI Approved :: Apache Software License
Classifier: Programming Language :: Python :: 2.7
